<?xml version="1.0"?>
<!DOCTYPE div SYSTEM "../dtd/tei-epidoc.dtd">
<!-- Start CVS information: do not remove -->
<!-- $Header: /data/epidoc/cvs/epidoc-cvsbackup/guidelines/src/ilonga.xml,v 1.14 2006-04-18 19:52:26 paregorios Exp $ -->
<!-- End CVS information: do not remove -->

<div xmlns="http://www.tei-c.org/ns/1.0" id="ilonga" lang="en">
   <head>"I longa"</head>
   <div id="ilonga-notes" type="gl-notes">
      <head>Notes</head>
      <p>The Latin term "i longa" is used by modern epigraphers to denote elongated (or tall) "i", a character originally intended to mark a double "i" or a long vowel quantity (e.g. "DIs" for "Diis") but employed indiscriminately for long or short "i" throughout the late Republic and imperial period.</p>
      <p>Of the typographic exempla consulted for the EpiDoc guidelines, only one addresses this case (<bibl><title level="a" type="abbreviated"><xref href="bibliography.xml#dohnicht">Dohnicht</xref></title>, <abbr expan="page">p.</abbr><biblScope type="pages">3</biblScope></bibl>, who recommends: ì, easily confounded with characters bearing apices). For the purpose of EpiDoc markup, we advise primary encoding indicating the <hi rend="strong">appearance</hi> of the character (see <xref href="tallcharacters.xml">Tall Characters</xref>). Secondary markup may then be applied to indicate editorial observations concerning the significance of the character's appearance (see, e.g., <xref href="vowelquantity.xml">Vowel Quantity</xref>).</p>
   </div>
   <div id="ilonga-responsibility" type="gl-responsibility">
      <head>Responsibility for this section</head>
      <listBibl>
         <bibl><respStmt><resp>author</resp><name>Tom Elliott</name></respStmt></bibl>
         <bibl><respStmt><resp>author</resp><name>John Bodel</name></respStmt></bibl>
         <bibl><respStmt><resp>converted XML</resp><name>Gabriel Bodard</name></respStmt></bibl>
         <bibl><respStmt><resp>assistance</resp><name>Lisa Anderson</name></respStmt></bibl>
      </listBibl>
   </div>
   <div id="ilonga-cvs" type="gl-cvs">
      <head><abbr expan="Concurrent Versioning System">CVS</abbr> Information</head>
      <p id="ilonga-cvs-revision-number">Revision number: <seg n="cvs-revision-number">$Revision: 1.14 $</seg></p>
      <p id="ilonga-cvs-revision-name">Revision name (if any): <seg n="cvs-revision-name">$Name: not supported by cvs2svn $</seg></p>
      <p id="ilonga-cvs-revision-date">Revision date: <seg n="cvs-revision-date">$Date: 2006-04-18 19:52:26 $</seg></p>
      <p id="ilonga-cvs-revision-author">Revision committed by: <seg n="cvs-revision-author">$Author: paregorios $</seg></p>
   </div>
</div>
