<?xml version="1.0" encoding="UTF-8"?>

<!-- Start license statement: do not remove 

EpiDoc: Guidelines for Structured Markup of Epigraphic Texts in TEI
Copyright (C) 2000-2006 by all contributors listed in <div type="gl-responsibility">, below.
Additional contributors' copyright may be designated in individual source files.

This program is free software; you can redistribute it and/or
modify it under the terms of the GNU General Public License
as published by the Free Software Foundation; either version 2
of the License, or (at your option) any later version.

This program is distributed in the hope that it will be useful,
but WITHOUT ANY WARRANTY; without even the implied warranty of
MERCHANTABILITY or FITNESS FOR A PARTICULAR PURPOSE.  See the
GNU General Public License for more details.

You should have received a copy of the GNU General Public License
along with this program; if not, write to the Free Software
Foundation, Inc., 51 Franklin Street, Fifth Floor, Boston, MA  02110-1301, USA.

Information about the EpiDoc community can be obtained via 
http://epidoc.sf.net.

End license statement: do not remove -->
<!DOCTYPE div SYSTEM "./dtd/tei-epidoc.dtd">
<!-- Start CVS information: do not remove -->

        <!-- $Header$ -->

        <!-- End CVS information: do not remove -->

        <div xmlns="http://www.tei-c.org/ns/1.0" xmlns:tei="http://www.tei-c.org/ns/1.0" xmlns:xi="http://www.w3.org/2001/XInclude" id="damagegroup"><head>Damaged area with characters wholly lost (both supplied and not)</head>
<div id="damagegroup-typographic" type="gl-typographic">
      <head>Traditional typographic representation</head>
      <list type="simple">
          <item><bibl><title level="a" type="abbreviated"><xref href="bibliography.xml#dohnicht" >Dohnicht</xref></title>, <abbr expan="page">p.</abbr><biblScope type="pages">4</biblScope></bibl>:
              <p>When a lost and supplemented sequence of characters includes the end of an inflected word, and it is impossible for the editor on the
              basis of context or comparanda to determine the original declension or conjugation of the word, and therefore the final characters for the supplement, 
              the editor places a single trailing horizontal dash within the square brackets, thus:</p>
            <list type="ordered">
                  <item id="TypoEx-1">[abc-]</item>      
            </list>
              </item>
      </list>
   </div><div id="damagegroup-regex" type="gl-regextest">
  <head>Regular Expression Test</head>
            <list><item id="Regex-1">
            blah</item>
</list><link id="TestLink-1" type="regextest" targets="TypoEx-1 EncEx-1 Regex-1"/></div><div id="damagegroup-edition" type="gl-edition" lang="la">
      <head lang="en">EpiDoc appearance with standard XSLT</head>
      <list type="ordered" lang="la">
         <item id="EncEx-1">
            <!--<tag>damage</tag>--><supplied reason="lost" cert="high">abc</supplied><gap reason="lost" extent="1" unit="character"/><!--<tag>/damage</tag>-->
         </item>
      </list>
   </div><div id="damagegroup-questions" type="gl-questions">
      <head>Questions and issues</head>
      <list type="unordered">
         <item>none</item>
      </list>
   </div><div id="damagegroup-tei-p4links">
      <head>TEI P4 links</head>
      <list type="simple">
         <item><xref href="http://www.tei-c.org/P4X/ref-DAMAGE.html" ><tag>damage</tag></xref></item>
         <item><xref href="http://www.tei-c.org/P4X/PH.html#PHCOMB" >18.2.4 Use of the Gap, Del, Damage, Unclear and Supplied Tags in Combination</xref></item>
      </list>
   </div><div id="damagegroup-responsibility" type="gl-responsibility">
      <head>Responsibility for this section</head>
      <listBibl>
         <bibl><respStmt><resp>author</resp><name>Tom Elliott</name></respStmt></bibl>
      </listBibl>
   </div><div id="damagegroup-cvs" type="gl-cvs">
      <head><abbr expan="Concurrent Versioning System">CVS</abbr> Information</head>
      <p id="damagegroup-cvs-revision-number">Revision number: <seg n="cvs-revision-number" cert="high" part="N">$Revision$</seg></p>
      <p id="damagegroup-cvs-revision-name">Revision name (if any): <seg n="cvs-revision-name" cert="high" part="N">$Name: not supported by cvs2svn $</seg></p>
      <p id="damagegroup-cvs-revision-date">Revision date: <seg n="cvs-revision-date" cert="high" part="N">$Date$</seg></p>
      <p id="damagegroup-cvs-revision-author">Revision committed by: <seg n="cvs-revision-author" cert="high" part="N">$Author$</seg></p>
   </div></div>

