<!-- Start license statement: do not remove 

EpiDoc: Guidelines for Structured Markup of Epigraphic Texts in TEI
Edition 8 copyright © 2008-2014 by all contributors listed in <div type="gl-responsibility">, below.
Additional contributors' copyright may be designated in individual source files.

This program is free software; you can redistribute it and/or
modify it under the terms of the GNU General Public License
as published by the Free Software Foundation; either version 2
of the License, or (at your option) any later version.

This program is distributed in the hope that it will be useful,
but WITHOUT ANY WARRANTY; without even the implied warranty of
MERCHANTABILITY or FITNESS FOR A PARTICULAR PURPOSE.  See the
GNU General Public License for more details.

You should have received a copy of the GNU General Public License
along with this program; if not, write to the Free Software
Foundation, Inc., 51 Franklin Street, Fifth Floor, Boston, MA  02110-1301, USA.

Information about the EpiDoc community can be obtained via 
http://epidoc.sf.net.

End license statement: do not remove -->
<!-- $Header: https://epidoc.svn.sourceforge.net/svnroot/epidoc/trunk/guidelines/xml-p5/xml/introeps.xml 1159 2010-05-14 11:02:59Z paregorios $ -->
<?oxygen NVDLSchema="../schema/epidoc.nvdl"?>

<div xmlns="http://www.tei-c.org/ns/1.0" xml:id="trans-numunknown" xml:lang="en">
    <head>Numbers/numerals of Unknown Value</head>
    <p><!-- gloss --></p>
    <p><specList>
        <specDesc key="num"/>
    </specList>
        <!--<listRef>
            <ptr target="a"/>
            </listRef>--></p> 
    
    <p>The numeral should be placed inside a <gi>num</gi>, but where its value is unknown, no
        <att>value</att> can be given.</p>
    
    <cit>
        <quote><!-- conventional rendering --></quote>
        <bibl corresp="#panciera">
            <biblScope>...</biblScope>
        </bibl>
        <bibl corresp="#ddbdp"/>
        <!-- etc. -->
    </cit>
    
    <egXML xmlns="http://www.tei-c.org/ns/Examples" corresp="#panciera">
        <num></num>
    </egXML>
    
    <egXML xmlns="http://www.tei-c.org/ns/Examples" rend="london" corresp="http://inslib.kcl.ac.uk/irt2009/IRT021.html#al1">
        <num><gap reason="lost" atLeast="1" atMost="4" unit="character"/></num>
    </egXML>
    
    <egXML xmlns="http://www.tei-c.org/ns/Examples" rend="ddbdp" corresp="http://papyri.info/ddbdp/o.abu.mina;;307#3">
        <num><gap reason="illegible" quantity="1" unit="character"/></num>
    </egXML>
    
    <div xml:id="trans-numunknown-responsibility">
    
        <head>Responsibility for this section</head>
        <listBibl>
            <bibl><respStmt>
                <resp>author</resp>
                <name>Scott Vanderbilt</name>
            </respStmt></bibl>
            <bibl><respStmt>
                <resp>author</resp>
                <name>Charlotte Tupman</name>
                <name/>
            </respStmt></bibl>
        </listBibl>
    </div>
</div>
